CPU/modules/CSR_File.v
`include "modules/headers/csr_funct3.vh"

module CSRFile #(
    parameter XLEN = 32
)(
    input clk,
    input clk_enable,
    input reset,
    input trapped,
    input mret_executed,
    input csr_write_enable,
    input [11:0] csr_read_address,
    input [11:0] csr_write_address,
    input [XLEN-1:0] csr_write_data,
    input instruction_retired,
    input valid_csr_address,
    input timer_interrupt_pending,

    output reg [XLEN-1:0] csr_read_out,
    output reg csr_ready
);

    wire [XLEN-1:0] mvendorid = 32'h52_56_4B_43;
    wire [XLEN-1:0] marchid   = 32'h34_36_53_35;
    wire [XLEN-1:0] mimpid    = 32'h34_36_49_31;
    wire [XLEN-1:0] mhartid   = 32'h52_4B_43_30;
    
    reg MIE;
    reg MPIE;
    wire [1:0] MPP = 2'b11;
    wire [XLEN-1:0] mstatus = {19'b0, MPP, 3'b0, MPIE, 3'b0, MIE, 3'b0};
    
    wire [XLEN-1:0] misa = 32'h40000100;
    wire [XLEN-1:0] mip  = {24'b0, timer_interrupt_pending, 7'b0};

    reg [XLEN-1:0] mtvec;
    reg [XLEN-1:0] mepc;
    reg [XLEN-1:0] mcause;

    reg [63:0] mcycle;
    reg [63:0] minstret;

    reg csr_processing;
    reg [XLEN-1:0] csr_read_data;

    wire csr_access;
    assign csr_access = valid_csr_address;

    localparam [XLEN-1:0] DEFAULT_mtvec  = 32'h00001000;
    localparam [XLEN-1:0] DEFAULT_mepc   = {XLEN{1'b0}};
    localparam [XLEN-1:0] DEFAULT_mcause = {XLEN{1'b0}};
    localparam [63:0] DEFAULT_mcycle = 64'b0;
    localparam [63:0] DEFAULT_minstret = 64'b0;

    always @(*) begin
      case (csr_read_address)
        12'hB00: csr_read_data = mcycle[XLEN-1:0];
        12'hB02: csr_read_data = minstret[XLEN-1:0];
        12'hB80: csr_read_data = mcycle[63:32];
        12'hB82: csr_read_data = minstret[63:32];
        12'hF11: csr_read_data = mvendorid;
        12'hF12: csr_read_data = marchid;
        12'hF13: csr_read_data = mimpid;
        12'hF14: csr_read_data = mhartid;
        12'h300: csr_read_data = mstatus;
        12'h301: csr_read_data = misa;
        12'h305: csr_read_data = mtvec;
        12'h341: csr_read_data = mepc;
        12'h342: csr_read_data = mcause;
        12'h344: csr_read_data = mip;
        default: csr_read_data = {XLEN{1'b0}};
      endcase

      if (reset) begin
        csr_ready = 1'b1;
      end else begin
        if (csr_access && !csr_processing) begin
          csr_ready = 1'b0;
        end else if (csr_processing) begin
          csr_ready = 1'b1;
        end else begin
          csr_ready = 1'b1;
        end
      end
    end

    always @(posedge clk or posedge reset) begin
      if (reset) begin
        mtvec   <= DEFAULT_mtvec;
        mepc    <= DEFAULT_mepc;
        mcause  <= DEFAULT_mcause;
        mcycle  <= DEFAULT_mcycle;
        minstret <= DEFAULT_minstret;

        csr_processing <= 1'b0;
        csr_read_out <= {XLEN{1'b0}};
        
        MIE  <= 1'b0;
        MPIE <= 1'b0;
      end else if (clk_enable) begin
        mcycle <= mcycle + 1;
        
        if (instruction_retired) begin
          minstret <= minstret + 1;
        end

        if (trapped) begin
            MPIE <= MIE;
            MIE  <= 1'b0;
        end 
        else if (mret_executed) begin
            MIE  <= MPIE;
            MPIE <= 1'b1;
        end 
        else if (csr_write_enable && (csr_write_address == 12'h300)) begin
            MIE  <= csr_write_data[3];
            MPIE <= csr_write_data[7];
        end

        if (csr_access && !csr_processing) begin
          csr_processing <= 1'b1;
          csr_read_out <= csr_read_data;
        end else if (csr_processing) begin
          csr_processing <= 1'b0;
          csr_read_out <= csr_read_data;
        end else if (csr_write_enable) begin
          csr_read_out <= csr_read_data;
        end

        if ((trapped && csr_write_enable) || (csr_write_enable)) begin
          case (csr_write_address)
            12'h305: mtvec  <= csr_write_data;
            12'h341: mepc   <= csr_write_data;
            12'h342: mcause <= csr_write_data;
            default: ;
          endcase
        end
      end
    end

endmodule

CPU/testbenches/CSR_File_tb.v
`timescale 1ns/1ps

module CSRFile_tb;
    reg         clk;
    reg         reset;
    reg         trapped;
    reg         mret_executed;
    reg         csr_write_enable;
    reg  [11:0] csr_read_address;
    reg  [11:0] csr_write_address;
    reg  [31:0] csr_write_data;
    reg instruction_retired;
    reg timer_interrupt_pending;

    wire [31:0] csr_read_out;
    wire        csr_ready;

    CSRFile csr_file (
        .clk(clk),
        .clk_enable(1'b1),
        .reset(reset),
        .trapped(trapped),
        .mret_executed(mret_executed),
        .csr_write_enable(csr_write_enable),
        .csr_read_address(csr_read_address),
        .csr_write_address(csr_write_address),
        .csr_write_data(csr_write_data),
        .instruction_retired(instruction_retired),
        .valid_csr_address(1'b1),
        .timer_interrupt_pending(timer_interrupt_pending),

        .csr_read_out(csr_read_out),
        .csr_ready(csr_ready)
    );

    initial clk = 0;
    always #5 clk = ~clk;

    initial begin
        $dumpfile("wave.vcd"); 
        $dumpvars(0, CSRFile_tb);

        $display("==================== CSR File Test START ====================");
        
        reset = 1;
        trapped = 0;
        mret_executed = 0;
        timer_interrupt_pending = 0;
        csr_write_enable = 0;
        csr_read_address = 12'h000;
        csr_write_address = 12'h000;
        csr_write_data = 32'h0;
        instruction_retired = 0;
        #10;
        reset = 0;
        #10;
        
        csr_read_address = 12'hF11; #10; 
        $display("mvendorid = %h (expected 52564B43)", csr_read_out);
        
        csr_read_address = 12'hF12; #10; 
        instruction_retired = 1'b1; #10;
        instruction_retired = 1'b0;
        $display("marchid = %h (expected 34365335)", csr_read_out);
        
        csr_read_address = 12'hF13; #10;
        $display("mimpid = %h (expected 34364931)", csr_read_out);

        csr_read_address = 12'hF14; #10; 
        $display("mhartid = %h (expected 524B4330)", csr_read_out);

        csr_read_address = 12'h300; #10; 
        $display("mstatus = %h (expected 00001800)", csr_read_out);

        csr_read_address = 12'h301; #10; 
        $display("misa = %h (expected 40000100)", csr_read_out);
        
        csr_read_address = 12'h305; #10; 
        $display("mtvec (reset) = %h (expected 00001000)", csr_read_out);
        csr_read_address = 12'h341; #10; 
        $display("mepc  (reset) = %h (expected 00000000)", csr_read_out);
        csr_read_address = 12'h342; #10; 
        $display("mcause(reset) = %h (expected 00000000)", csr_read_out);

        csr_read_address = 12'h305; #10; 
        $display("mtvec = %h (expected 00001000)", csr_read_out);

        csr_write_address = 12'h305;
        csr_write_data = 32'h00003000;
        csr_write_enable = 1;
        #10;

        csr_write_enable = 0;
        #10;

        csr_read_address = 12'h305; #10; 
        $display("mtvec = %h (expected 00003000)", csr_read_out);
        
        csr_read_address = 12'h341; #10;
        $display("mepc = %h (expected 00000000)", csr_read_out);

        csr_write_address = 12'h341;
        csr_write_data = 32'h00004000;
        csr_write_enable = 1;
        #10;

        csr_write_enable = 0;
        #10;

        csr_read_address = 12'h341; #10; 
        $display("mepc = %h (expected 00004000)", csr_read_out);
        
        csr_read_address = 12'h342; #10; 
        $display("mcause = %h (expected 00000000)", csr_read_out);

        csr_write_address = 12'h342;
        csr_write_data = 32'h00000004;
        csr_write_enable = 1;
        #10;

        csr_write_enable = 0;
        #10;

        csr_read_address = 12'h342;
        #10;

        $display("mcause = %h (expected 00000004)", csr_read_out);
        
        csr_read_address = 12'hF11; #10; 
        $display("Read-only test : mvendorid = %h (expected 52564B43)", csr_read_out);

        csr_write_address = 12'hF11;
        csr_write_data = 32'h00003000;
        csr_write_enable = 1;
        #10;

        csr_write_enable = 0;
        #10;

        csr_read_address = 12'hF11;
        #10;

        $display("Write ignored : mvendorid = %h (expected 52564B43)", csr_read_out);
        
        csr_read_address = 12'hB00; #10;
        $display("mcycle (lower 32-bit) = %h (auto-incremented, not 0)", csr_read_out);
        
        csr_read_address = 12'hB80; #10;
        $display("mcycleh (upper 32-bit) = %h (should be 0, no overflow yet)", csr_read_out);
        
        csr_read_address = 12'hB02; #10;
        $display("minstret (lower 32-bit) = %h (should be 1, one instruction retired in Test 1)", csr_read_out);
        
        csr_read_address = 12'hB82; #10;
        $display("minstreth (upper 32-bit) = %h (should be 0, no overflow yet)", csr_read_out);

        csr_read_address = 12'hB00; #10;
        $display("mcycle (before write attempt) = %h", csr_read_out);

        csr_write_address = 12'hB00;
        csr_write_data = 32'h12345678;
        csr_write_enable = 1;
        #10;

        csr_write_enable = 0;
        #10;

        csr_read_address = 12'hB00; #10;
        $display("mcycle (after write attempt) = %h (write should be ignored, auto-incremented)", csr_read_out);
        
        csr_read_address = 12'hB80; #10;
        $display("mcycleh (before write attempt) = %h", csr_read_out);

        csr_write_address = 12'hB80;
        csr_write_data = 32'hABCDEF00;
        csr_write_enable = 1;
        #10;

        csr_write_enable = 0;
        #10;

        csr_read_address = 12'hB80; #10;
        $display("mcycleh (after write attempt) = %h (write should be ignored, should remain 0)", csr_read_out);
        
        csr_read_address = 12'hB02; #10;
        $display("minstret (before write attempt) = %h", csr_read_out);

        csr_write_address = 12'hB02;
        csr_write_data = 32'hDEADBEEF;
        csr_write_enable = 1;
        #10;

        csr_write_enable = 0;
        #10;

        csr_read_address = 12'hB02; #10;
        $display("minstret (after write attempt) = %h (write should be ignored, should remain 1)", csr_read_out);
        
        csr_read_address = 12'hB82; #10;
        $display("minstreth (before write attempt) = %h", csr_read_out);

        csr_write_address = 12'hB82;
        csr_write_data = 32'hCAFEBABE;
        csr_write_enable = 1;
        #10;

        csr_write_enable = 0;
        #10;

        csr_read_address = 12'hB82; #10;
        $display("minstreth (after write attempt) = %h (write should be ignored, should remain 0)", csr_read_out);
        
        $display("\n=== Auto-increment verification ===");
        csr_read_address = 12'hB00; 
        #10;
        $display("mcycle at T0 = %h", csr_read_out);
        #20; 
        csr_read_address = 12'hB00; 
        #10;
        $display("mcycle at T0+2 = %h (should be +2 from previous)", csr_read_out);
        
        $display("\n=== instruction_retired test ===");
        csr_read_address = 12'hB02;
        #10;
        $display("minstret before retired = %h", csr_read_out);
        
        instruction_retired = 1;
        #10;
        instruction_retired = 0;
        csr_read_address = 12'hB02;
        #10;
        $display("minstret after 1 retired = %h (should be +1)", csr_read_out);
        
        instruction_retired = 1;
        #10;
        instruction_retired = 1;
        #10;
        instruction_retired = 0;
        csr_read_address = 12'hB02;
        #10;
        $display("minstret after 2 more retired = %h (should be +2)", csr_read_out);

        csr_read_address = 12'h344; #10;
        $display("mip = %b (MTIP should be 0)", csr_read_out);
        timer_interrupt_pending = 1;
        #20;
        csr_read_address = 12'h344; #10;
        $display("mip = %b (MTIP should be 1)", csr_read_out);

        $display("\n=== Test 14: Trap & mret Verification ===");
        csr_write_address = 12'h300; 
        csr_write_data = 32'h00000008;
        csr_write_enable = 1; #10;
        csr_write_enable = 0; #10;
        
        csr_read_address = 12'h300; #10;
        $display("Before Trap: mstatus = %h (Expected MIE=1, MPIE=0 -> 00000008)", csr_read_out);

        trapped = 1; #10;
        trapped = 0; #10;
        
        csr_read_address = 12'h300; #10;
        $display("After Trap:  mstatus = %h (Expected MIE=0, MPIE=1 -> 00000080)", csr_read_out);

        mret_executed = 1; #10;
        mret_executed = 0; #10;
        
        csr_read_address = 12'h300; #10;
        $display("After mret:  mstatus = %h (Expected MIE=1, MPIE=1 -> 00000088)", csr_read_out);

        $display("\n=== Final Counter Values ===");
        csr_read_address = 12'hB00; #10;
        $display("Final mcycle[31:0] = %h", csr_read_out);
        
        csr_read_address = 12'hB80; #10;
        $display("Final mcycle[63:32] = %h", csr_read_out);
        $display("Final Full mcycle = 0x%h_%h", csr_file.mcycle[63:32], csr_file.mcycle[31:0]);
        
        csr_read_address = 12'hB02; #10;
        $display("Final minstret[31:0] = %h", csr_read_out);
        
        csr_read_address = 12'hB82; #10;
        $display("Final minstret[63:32] = %h", csr_read_out);
        $display("Final Full minstret = 0x%h_%h", csr_file.minstret[63:32], csr_file.minstret[31:0]);
        
        $display("\n====================  CSR File Test END  ====================");
        $finish;
    end
    
endmodule

CPU/wave.vcd
$date
	Fri Apr 03 13:06:38 2026
$end
$version
	Icarus Verilog
$end
$timescale
	1ps
$end
$scope module CSRFile_tb $end
$var wire 1 ! csr_ready $end
$var wire 32 " csr_read_out [31:0] $end
$var reg 1 # clk $end
$var reg 12 $ csr_read_address [11:0] $end
$var reg 12 % csr_write_address [11:0] $end
$var reg 32 & csr_write_data [31:0] $end
$var reg 1 ' csr_write_enable $end
$var reg 1 ( instruction_retired $end
$var reg 1 ) mret_executed $end
$var reg 1 * reset $end
$var reg 1 + timer_interrupt_pending $end
$var reg 1 , trapped $end
$scope module csr_file $end
$var wire 2 - MPP [1:0] $end
$var wire 1 # clk $end
$var wire 1 . clk_enable $end
$var wire 1 / csr_access $end
$var wire 12 0 csr_read_address [11:0] $end
$var wire 12 1 csr_write_address [11:0] $end
$var wire 32 2 csr_write_data [31:0] $end
$var wire 1 ' csr_write_enable $end
$var wire 1 ( instruction_retired $end
$var wire 32 3 marchid [31:0] $end
$var wire 32 4 mhartid [31:0] $end
$var wire 32 5 mimpid [31:0] $end
$var wire 32 6 misa [31:0] $end
$var wire 1 ) mret_executed $end
$var wire 32 7 mvendorid [31:0] $end
$var wire 1 * reset $end
$var wire 1 + timer_interrupt_pending $end
$var wire 1 , trapped $end
$var wire 1 8 valid_csr_address $end
$var wire 32 9 mstatus [31:0] $end
$var wire 32 : mip [31:0] $end
$var parameter 32 ; DEFAULT_mcause $end
$var parameter 64 < DEFAULT_mcycle $end
$var parameter 32 = DEFAULT_mepc $end
$var parameter 64 > DEFAULT_minstret $end
$var parameter 32 ? DEFAULT_mtvec $end
$var parameter 32 @ XLEN $end
$var reg 1 A MIE $end
$var reg 1 B MPIE $end
$var reg 1 C csr_processing $end
$var reg 32 D csr_read_data [31:0] $end
$var reg 32 E csr_read_out [31:0] $end
$var reg 1 ! csr_ready $end
$var reg 32 F mcause [31:0] $end
$var reg 64 G mcycle [63:0] $end
$var reg 32 H mepc [31:0] $end
$var reg 64 I minstret [63:0] $end
$var reg 32 J mtvec [31:0] $end
$upscope $end
$upscope $end
$enddefinitions $end
$comment Show the parameter values. $end
$dumpall
b100000 @
b1000000000000 ?
b0 >
b0 =
b0 <
b0 ;
$end
#0
$dumpvars
b1000000000000 J
b0 I
b0 H
b0 G
b0 F
b0 E
b0 D
0C
1B
0A
b0 :
b1100010000000 9
18
b1010010010101100100101101000011 7
b1000000000000000000000100000000 6
b110100001101100100100100110001 5
b1010010010010110100001100110000 4
b110100001101100101001100110101 3
b0 2
b0 1
b0 0
1/
1.
b11 -
0,
0+
1*
0)
0(
0'
b0 &
b0 %
b0 $
0#
b0 "
1!
$end
#5000
1#
#10000
0!
0#
0*
#15000
1!
1C
b1 G
1#
#20000
b1010010010101100100101101000011 D
0#
b111100010001 $
b111100010001 0
#25000
0!
b1010010010101100100101101000011 "
b1010010010101100100101101000011 E
0C
b10 G
1#
#30000
b110100001101100101001100110101 D
0#
b111100010010 $
b111100010010 0
#35000
1!
b110100001101100101001100110101 "
b110100001101100101001100110101 E
1C
b11 G
1#
#40000
0#
1(
#45000
0!
0C
b1 I
b100 G
1#
#50000
b110100001101100100100100110001 D
0#
b111100010011 $
b111100010011 0
0(
#55000
1!
b110100001101100100100100110001 "
b110100001101100100100100110001 E
1C
b101 G
1#
#60000
b1010010010010110100001100110000 D
0#
b111100010100 $
b111100010100 0
#65000
0!
b1010010010010110100001100110000 "
b1010010010010110100001100110000 E
0C
b110 G
1#
#70000
b1100010000000 D
0#
b1100000000 $
b1100000000 0
#75000
1!
b1100010000000 "
b1100010000000 E
1C
b111 G
1#
#80000
b1000000000000000000000100000000 D
0#
b1100000001 $
b1100000001 0
#85000
0!
b1000000000000000000000100000000 "
b1000000000000000000000100000000 E
0C
b1000 G
1#
#90000
b1000000000000 D
0#
b1100000101 $
b1100000101 0
#95000
1!
b1000000000000 "
b1000000000000 E
1C
b1001 G
1#
#100000
b0 D
0#
b1101000001 $
b1101000001 0
#105000
0!
b0 "
b0 E
0C
b1010 G
1#
#110000
0#
b1101000010 $
b1101000010 0
#115000
1!
1C
b1011 G
1#
#120000
b1000000000000 D
0#
b1100000101 $
b1100000101 0
#125000
0!
b1000000000000 "
b1000000000000 E
0C
b1100 G
1#
#130000
0#
1'
b11000000000000 &
b11000000000000 2
b1100000101 %
b1100000101 1
#135000
1!
b11000000000000 D
b11000000000000 J
1C
b1101 G
1#
#140000
0#
0'
#145000
0!
b11000000000000 "
b11000000000000 E
0C
b1110 G
1#
#150000
0#
#155000
1!
1C
b1111 G
1#
#160000
b0 D
0#
b1101000001 $
b1101000001 0
#165000
0!
b0 "
b0 E
0C
b10000 G
1#
#170000
0#
1'
b100000000000000 &
b100000000000000 2
b1101000001 %
b1101000001 1
#175000
1!
b100000000000000 D
b100000000000000 H
1C
b10001 G
1#
#180000
0#
0'
#185000
0!
b100000000000000 "
b100000000000000 E
0C
b10010 G
1#
#190000
0#
#195000
1!
1C
b10011 G
1#
#200000
b0 D
0#
b1101000010 $
b1101000010 0
#205000
0!
b0 "
b0 E
0C
b10100 G
1#
#210000
0#
1'
b100 &
b100 2
b1101000010 %
b1101000010 1
#215000
1!
b100 D
b100 F
1C
b10101 G
1#
#220000
0#
0'
#225000
0!
b100 "
b100 E
0C
b10110 G
1#
#230000
0#
#235000
1!
1C
b10111 G
1#
#240000
b1010010010101100100101101000011 D
0#
b111100010001 $
b111100010001 0
#245000
0!
b1010010010101100100101101000011 "
b1010010010101100100101101000011 E
0C
b11000 G
1#
#250000
0#
1'
b11000000000000 &
b11000000000000 2
b111100010001 %
b111100010001 1
#255000
1!
1C
b11001 G
1#
#260000
0#
0'
#265000
0!
0C
b11010 G
1#
#270000
0#
#275000
1!
1C
b11011 G
1#
#280000
b11011 D
0#
b101100000000 $
b101100000000 0
#285000
0!
b11100 D
b11011 "
b11011 E
0C
b11100 G
1#
#290000
b0 D
0#
b101110000000 $
b101110000000 0
#295000
1!
b0 "
b0 E
1C
b11101 G
1#
#300000
b1 D
0#
b101100000010 $
b101100000010 0
#305000
0!
b1 "
b1 E
0C
b11110 G
1#
#310000
b0 D
0#
b101110000010 $
b101110000010 0
#315000
1!
b0 "
b0 E
1C
b11111 G
1#
#320000
b11111 D
0#
b101100000000 $
b101100000000 0
#325000
0!
b100000 D
b11111 "
b11111 E
0C
b100000 G
1#
#330000
0#
1'
b10010001101000101011001111000 &
b10010001101000101011001111000 2
b101100000000 %
b101100000000 1
#335000
1!
b100001 D
b100000 "
b100000 E
1C
b100001 G
1#
#340000
0#
0'
#345000
0!
b100010 D
b100001 "
b100001 E
0C
b100010 G
1#
#350000
0#
#355000
1!
b100011 D
b100010 "
b100010 E
1C
b100011 G
1#
#360000
b0 D
0#
b101110000000 $
b101110000000 0
#365000
0!
b0 "
b0 E
0C
b100100 G
1#
#370000
0#
1'
b10101011110011011110111100000000 &
b10101011110011011110111100000000 2
b101110000000 %
b101110000000 1
#375000
1!
1C
b100101 G
1#
#380000
0#
0'
#385000
0!
0C
b100110 G
1#
#390000
0#
#395000
1!
1C
b100111 G
1#
#400000
b1 D
0#
b101100000010 $
b101100000010 0
#405000
0!
b1 "
b1 E
0C
b101000 G
1#
#410000
0#
1'
b11011110101011011011111011101111 &
b11011110101011011011111011101111 2
b101100000010 %
b101100000010 1
#415000
1!
1C
b101001 G
1#
#420000
0#
0'
#425000
0!
0C
b101010 G
1#
#430000
0#
#435000
1!
1C
b101011 G
1#
#440000
b0 D
0#
b101110000010 $
b101110000010 0
#445000
0!
b0 "
b0 E
0C
b101100 G
1#
#450000
0#
1'
b11001010111111101011101010111110 &
b11001010111111101011101010111110 2
b101110000010 %
b101110000010 1
#455000
1!
1C
b101101 G
1#
#460000
0#
0'
#465000
0!
0C
b101110 G
1#
#470000
0#
#475000
1!
1C
b101111 G
1#
#480000
b101111 D
0#
b101100000000 $
b101100000000 0
#485000
0!
b110000 D
b101111 "
b101111 E
0C
b110000 G
1#
#490000
0#
#495000
1!
b110001 D
b110000 "
b110000 E
1C
b110001 G
1#
#500000
0#
#505000
0!
b110010 D
b110001 "
b110001 E
0C
b110010 G
1#
#510000
0#
#515000
1!
b110011 D
b110010 "
b110010 E
1C
b110011 G
1#
#520000
b1 D
0#
b101100000010 $
b101100000010 0
#525000
0!
b1 "
b1 E
0C
b110100 G
1#
#530000
0#
1(
#535000
1!
b10 D
1C
b10 I
b110101 G
1#
#540000
0#
0(
#545000
0!
b10 "
b10 E
0C
b110110 G
1#
#550000
0#
1(
#555000
1!
b11 D
1C
b11 I
b110111 G
1#
#560000
0#
#565000
0!
b100 D
b11 "
b11 E
0C
b100 I
b111000 G
1#
#570000
0#
0(
#575000
1!
b100 "
b100 E
1C
b111001 G
1#
#580000
b0 D
0#
b1101000100 $
b1101000100 0
#585000
0!
b0 "
b0 E
0C
b111010 G
1#
#590000
b10000000 D
0#
b10000000 :
1+
#595000
1!
b10000000 "
b10000000 E
1C
b111011 G
1#
#600000
0#
#605000
0!
0C
b111100 G
1#
#610000
0#
#615000
1!
1C
b111101 G
1#
#620000
0#
1'
b1000 &
b1000 2
b1100000000 %
b1100000000 1
#625000
0!
0C
0B
b1100000001000 9
1A
b111110 G
1#
#630000
0#
0'
#635000
1!
1C
b111111 G
1#
#640000
b1100000001000 D
0#
b1100000000 $
b1100000000 0
#645000
0!
b1100000001000 "
b1100000001000 E
0C
b1000000 G
1#
#650000
0#
1,
#655000
1!
b1100010000000 D
1C
0A
b1100010000000 9
1B
b1000001 G
1#
#660000
0#
0,
#665000
0!
b1100010000000 "
b1100010000000 E
0C
b1000010 G
1#
#670000
0#
#675000
1!
1C
b1000011 G
1#
#680000
0#
1)
#685000
0!
b1100010001000 D
0C
b1100010001000 9
1A
b1000100 G
1#
#690000
0#
0)
#695000
1!
b1100010001000 "
b1100010001000 E
1C
b1000101 G
1#
#700000
0#
#705000
0!
0C
b1000110 G
1#
#710000
b1000110 D
0#
b101100000000 $
b101100000000 0
#715000
1!
b1000111 D
b1000110 "
b1000110 E
1C
b1000111 G
1#
#720000
b0 D
0#
b101110000000 $
b101110000000 0
#725000
0!
b0 "
b0 E
0C
b1001000 G
1#
#730000
b100 D
0#
b101100000010 $
b101100000010 0
#735000
1!
b100 "
b100 E
1C
b1001001 G
1#
#740000
b0 D
0#
b101110000010 $
b101110000010 0
#745000
0!
b0 "
b0 E
0C
b1001010 G
1#
